runner/__init__.py
runner/__main__.py
runner/concurrency.py
runner/configs.py
runner/scheduler.py
runner/stub_nvitop.py
runner/task.py
runner/tqdm_logger.py
runner/util.py
triage_runner-0.4.5.dist-info/METADATA
triage_runner-0.4.5.dist-info/WHEEL
triage_runner-0.4.5.dist-info/dependency_links.txt
triage_runner-0.4.5.dist-info/entry_points.txt
triage_runner-0.4.5.dist-info/top_level.txt
triage_runner-0.4.5.dist-info/RECORD
