Metadata-Version: 2.1
Name: triage-runner
Version: 0.4.5
Summary: Script running tool for optimizing GPU memory utilization.
Home-page: https://github.com/ViktorooReps/triage
Author: Viktor Scherbakov
Author-email: viktoroo.sch@gmail.com
License: MIT
Download-URL: https://github.com/ViktorooReps/triage/archive/0.0.1.tar.gz
Platform: UNKNOWN
Classifier: License :: OSI Approved :: MIT License
Classifier: Programming Language :: Python :: 3
Classifier: Programming Language :: Python :: 3.6
Classifier: Programming Language :: Python :: 3.11
Requires-Python: >=3.6
Requires-Dist: click
Requires-Dist: click-loglevel
Requires-Dist: tqdm
Requires-Dist: setuptools
Requires-Dist: nvitop
Requires-Dist: psutil
